{
  "frames": {
    "resource/stump-1.png": {
      "frame": {
        "x": 4,
        "y": 4,
        "w": 192,
        "h": 256
      },
      "rotated": false,
      "trimmed": false,
      "spriteSourceSize": {
        "x": 0,
        "y": 0,
        "w": 192,
        "h": 256
      },
      "sourceSize": {
        "w": 192,
        "h": 256
      }
    },
    "resource/stump-2.png": {
      "frame": {
        "x": 200,
        "y": 4,
        "w": 192,
        "h": 256
      },
      "rotated": false,
      "trimmed": false,
      "spriteSourceSize": {
        "x": 0,
        "y": 0,
        "w": 192,
        "h": 256
      },
      "sourceSize": {
        "w": 192,
        "h": 256
      }
    },
    "resource/stump-3.png": {
      "frame": {
        "x": 396,
        "y": 4,
        "w": 192,
        "h": 256
      },
      "rotated": false,
      "trimmed": false,
      "spriteSourceSize": {
        "x": 0,
        "y": 0,
        "w": 192,
        "h": 256
      },
      "sourceSize": {
        "w": 192,
        "h": 256
      }
    },
    "resource/stump-4.png": {
      "frame": {
        "x": 592,
        "y": 4,
        "w": 192,
        "h": 256
      },
      "rotated": false,
      "trimmed": false,
      "spriteSourceSize": {
        "x": 0,
        "y": 0,
        "w": 192,
        "h": 256
      },
      "sourceSize": {
        "w": 192,
        "h": 256
      }
    },
    "resource/gold.png": {
      "frame": {
        "x": 788,
        "y": 4,
        "w": 128,
        "h": 128
      },
      "rotated": false,
      "trimmed": false,
      "spriteSourceSize": {
        "x": 0,
        "y": 0,
        "w": 128,
        "h": 128
      },
      "sourceSize": {
        "w": 128,
        "h": 128
      }
    },
    "resource/gold-stone-1.png": {
      "frame": {
        "x": 4,
        "y": 268,
        "w": 128,
        "h": 128
      },
      "rotated": false,
      "trimmed": false,
      "spriteSourceSize": {
        "x": 0,
        "y": 0,
        "w": 128,
        "h": 128
      },
      "sourceSize": {
        "w": 128,
        "h": 128
      }
    },
    "resource/gold-stone-2.png": {
      "frame": {
        "x": 136,
        "y": 268,
        "w": 128,
        "h": 128
      },
      "rotated": false,
      "trimmed": false,
      "spriteSourceSize": {
        "x": 0,
        "y": 0,
        "w": 128,
        "h": 128
      },
      "sourceSize": {
        "w": 128,
        "h": 128
      }
    },
    "resource/gold-stone-3.png": {
      "frame": {
        "x": 268,
        "y": 268,
        "w": 128,
        "h": 128
      },
      "rotated": false,
      "trimmed": false,
      "spriteSourceSize": {
        "x": 0,
        "y": 0,
        "w": 128,
        "h": 128
      },
      "sourceSize": {
        "w": 128,
        "h": 128
      }
    },
    "resource/gold-stone-4.png": {
      "frame": {
        "x": 400,
        "y": 268,
        "w": 128,
        "h": 128
      },
      "rotated": false,
      "trimmed": false,
      "spriteSourceSize": {
        "x": 0,
        "y": 0,
        "w": 128,
        "h": 128
      },
      "sourceSize": {
        "w": 128,
        "h": 128
      }
    },
    "resource/gold-stone-5.png": {
      "frame": {
        "x": 532,
        "y": 268,
        "w": 128,
        "h": 128
      },
      "rotated": false,
      "trimmed": false,
      "spriteSourceSize": {
        "x": 0,
        "y": 0,
        "w": 128,
        "h": 128
      },
      "sourceSize": {
        "w": 128,
        "h": 128
      }
    },
    "resource/gold-stone-6.png": {
      "frame": {
        "x": 664,
        "y": 268,
        "w": 128,
        "h": 128
      },
      "rotated": false,
      "trimmed": false,
      "spriteSourceSize": {
        "x": 0,
        "y": 0,
        "w": 128,
        "h": 128
      },
      "sourceSize": {
        "w": 128,
        "h": 128
      }
    },
    "resource/meat.png": {
      "frame": {
        "x": 920,
        "y": 4,
        "w": 64,
        "h": 64
      },
      "rotated": false,
      "trimmed": false,
      "spriteSourceSize": {
        "x": 0,
        "y": 0,
        "w": 64,
        "h": 64
      },
      "sourceSize": {
        "w": 64,
        "h": 64
      }
    },
    "resource/wood.png": {
      "frame": {
        "x": 796,
        "y": 268,
        "w": 64,
        "h": 64
      },
      "rotated": false,
      "trimmed": false,
      "spriteSourceSize": {
        "x": 0,
        "y": 0,
        "w": 64,
        "h": 64
      },
      "sourceSize": {
        "w": 64,
        "h": 64
      }
    },
    "resource/tool-01.png": {
      "frame": {
        "x": 864,
        "y": 268,
        "w": 64,
        "h": 64
      },
      "rotated": false,
      "trimmed": false,
      "spriteSourceSize": {
        "x": 0,
        "y": 0,
        "w": 64,
        "h": 64
      },
      "sourceSize": {
        "w": 64,
        "h": 64
      }
    },
    "resource/tool-02.png": {
      "frame": {
        "x": 932,
        "y": 268,
        "w": 64,
        "h": 64
      },
      "rotated": false,
      "trimmed": false,
      "spriteSourceSize": {
        "x": 0,
        "y": 0,
        "w": 64,
        "h": 64
      },
      "sourceSize": {
        "w": 64,
        "h": 64
      }
    },
    "resource/tool-03.png": {
      "frame": {
        "x": 4,
        "y": 404,
        "w": 64,
        "h": 64
      },
      "rotated": false,
      "trimmed": false,
      "spriteSourceSize": {
        "x": 0,
        "y": 0,
        "w": 64,
        "h": 64
      },
      "sourceSize": {
        "w": 64,
        "h": 64
      }
    },
    "resource/tool-04.png": {
      "frame": {
        "x": 72,
        "y": 404,
        "w": 64,
        "h": 64
      },
      "rotated": false,
      "trimmed": false,
      "spriteSourceSize": {
        "x": 0,
        "y": 0,
        "w": 64,
        "h": 64
      },
      "sourceSize": {
        "w": 64,
        "h": 64
      }
    },
    "resource/rock-1.png": {
      "frame": {
        "x": 140,
        "y": 404,
        "w": 64,
        "h": 64
      },
      "rotated": false,
      "trimmed": false,
      "spriteSourceSize": {
        "x": 0,
        "y": 0,
        "w": 64,
        "h": 64
      },
      "sourceSize": {
        "w": 64,
        "h": 64
      }
    },
    "resource/rock-2.png": {
      "frame": {
        "x": 208,
        "y": 404,
        "w": 64,
        "h": 64
      },
      "rotated": false,
      "trimmed": false,
      "spriteSourceSize": {
        "x": 0,
        "y": 0,
        "w": 64,
        "h": 64
      },
      "sourceSize": {
        "w": 64,
        "h": 64
      }
    },
    "resource/rock-3.png": {
      "frame": {
        "x": 276,
        "y": 404,
        "w": 64,
        "h": 64
      },
      "rotated": false,
      "trimmed": false,
      "spriteSourceSize": {
        "x": 0,
        "y": 0,
        "w": 64,
        "h": 64
      },
      "sourceSize": {
        "w": 64,
        "h": 64
      }
    },
    "resource/rock-4.png": {
      "frame": {
        "x": 344,
        "y": 404,
        "w": 64,
        "h": 64
      },
      "rotated": false,
      "trimmed": false,
      "spriteSourceSize": {
        "x": 0,
        "y": 0,
        "w": 64,
        "h": 64
      },
      "sourceSize": {
        "w": 64,
        "h": 64
      }
    }
  },
  "meta": {
    "app": "tiny-swords-packed-atlas",
    "version": "1.0",
    "image": "tiny-swords-resources.png",
    "format": "RGBA8888",
    "size": {
      "w": 1024,
      "h": 512
    },
    "scale": 1
  }
}